cxvshifter/__init__.py
cxvshifter/cxvshifter.py
shifter/__init__.py
shifter/shifter.py
ctxvalue_shifter-1.2.1.dist-info/LICENSE
ctxvalue_shifter-1.2.1.dist-info/METADATA
ctxvalue_shifter-1.2.1.dist-info/WHEEL
ctxvalue_shifter-1.2.1.dist-info/top_level.txt
ctxvalue_shifter-1.2.1.dist-info/RECORD
