Metadata-Version: 2.1
Name: ctxvalue-shifter
Version: 1.2.1
Summary: Contextual Value Shifter, a module for shifting values to different destinations.
Author: Arsalan Kazmi
Author-email: sonicspeed848@gmail.com
Requires-Python: >=3.6
License-File: LICENSE
